lightpdf_aipdf_mcp/__init__.py
lightpdf_aipdf_mcp/api/__init__.py
lightpdf_aipdf_mcp/api/adapter.py
lightpdf_aipdf_mcp/api/server.py
lightpdf_aipdf_mcp/core/__init__.py
lightpdf_aipdf_mcp/core/processor.py
lightpdf_aipdf_mcp/models/__init__.py
lightpdf_aipdf_mcp/models/schemas.py
lightpdf_aipdf_mcp/services/__init__.py
lightpdf_aipdf_mcp/services/archiver.py
lightpdf_aipdf_mcp/services/converter.py
lightpdf_aipdf_mcp/services/create_pdf.py
lightpdf_aipdf_mcp/services/editor.py
lightpdf_aipdf_mcp/services/image_processor.py
lightpdf_aipdf_mcp/services/ocr.py
lightpdf_aipdf_mcp/services/summarizer.py
lightpdf_aipdf_mcp/services/translator.py
lightpdf_aipdf_mcp/utils/__init__.py
lightpdf_aipdf_mcp/utils/common.py
lightpdf_aipdf_mcp-0.1.180.dist-info/METADATA
lightpdf_aipdf_mcp-0.1.180.dist-info/WHEEL
lightpdf_aipdf_mcp-0.1.180.dist-info/entry_points.txt
lightpdf_aipdf_mcp-0.1.180.dist-info/RECORD
