Metadata-Version: 2.4
Name: lightpdf-aipdf-mcp
Version: 0.1.180
Summary: MCP Server for LightPDF AI-PDF
Author: LightPDF Team
License: Proprietary
Requires-Python: >=3.10
Requires-Dist: fastmcp
Requires-Dist: httpx
Requires-Dist: httpx-sse
Requires-Dist: mcp
Requires-Dist: mcp[cli]
Requires-Dist: pillow
Requires-Dist: pydantic
Requires-Dist: pydantic-settings
Requires-Dist: python-dotenv
Requires-Dist: starlette
Requires-Dist: uvicorn
